ecdysys/__init__.py
ecdysys/__main__.py
ecdysys/utils/main.py
ecdysys-0.1.9.dist-info/METADATA
ecdysys-0.1.9.dist-info/WHEEL
ecdysys-0.1.9.dist-info/entry_points.txt
ecdysys-0.1.9.dist-info/licenses/LICENSE
ecdysys-0.1.9.dist-info/RECORD
