Metadata-Version: 2.4
Name: ecdysys
Version: 0.1.9
Summary: Python CLI to update your system packages
Project-URL: Repository, https://github.com/claymorwan/ecdysys
Project-URL: Issues, https://github.com/claymorwan/ecdysys/issues
Project-URL: changelog, https://github.com/claymorwan/ecdysys/blob/main/CHANGELOG.md
Author-email: claymorwan <claymorwan@fembois.dev>
License-Expression: MIT
License-File: LICENSE
Classifier: Operating System :: POSIX :: Linux
Classifier: Programming Language :: Python :: 3
Requires-Python: >=3.13
Requires-Dist: colorama==0.4.6
Requires-Dist: yaspin>=3.1.0
